StableDiffusionAPI/Community.py
StableDiffusionAPI/SetKey.py
StableDiffusionAPI/Text2Img.py
StableDiffusionAPI/__init__.py
StableDiffusionAPI/__main__.py
StableDiffusionAPI/key.py
StableDiffusionAPI-0.0.5.dist-info/LICENSE
StableDiffusionAPI-0.0.5.dist-info/METADATA
StableDiffusionAPI-0.0.5.dist-info/WHEEL
StableDiffusionAPI-0.0.5.dist-info/top_level.txt
StableDiffusionAPI-0.0.5.dist-info/RECORD
