Metadata-Version: 2.1
Name: StableDiffusionAPI
Version: 0.0.5
Summary: A package to interface with the StableDiffusionAPI.com API
Author-email: Jonathan Caraveo <jon@ziawe.com>
Project-URL: Homepage, https://StableDiffusionAPI.com
Project-URL: GitHub, https://github.com/caraveo/SDAPI/
Project-URL: Bug Tracker, https://github.com/Caraveo/SDAPI/issues
Project-URL: Guide, https://www.sparkandwave.com/stablediffusionapi/
Classifier: Programming Language :: Python :: 3
Classifier: License :: OSI Approved :: MIT License
Classifier: Operating System :: OS Independent
Requires-Python: >=3.7
License-File: LICENSE
